react_pages/__init__.py
react_pages/cli.py
react_pages/core.py
react_pages/views.py
react_pages/management/__init__.py
react_pages/management/commands/__init__.py
react_pages/management/commands/react_pages.py
react_pages/management/commands/react_pages_develop.py
react_pages/nodejs/.env
react_pages/nodejs/.gitignore
react_pages/nodejs/package-lock.json
react_pages/nodejs/package.json
react_pages/nodejs/config/customPaths.js
react_pages/nodejs/config/env.js
react_pages/nodejs/config/paths.js
react_pages/nodejs/config/polyfills.js
react_pages/nodejs/config/webpack.config.dev.js
react_pages/nodejs/config/webpack.config.prod.js
react_pages/nodejs/config/webpackDevServer.config.js
react_pages/nodejs/config/custom-react-scripts/config.js
react_pages/nodejs/config/custom-react-scripts/customizers/babel-plugins.js
react_pages/nodejs/config/custom-react-scripts/customizers/babel-presets.js
react_pages/nodejs/config/custom-react-scripts/customizers/webpack-loaders.js
react_pages/nodejs/config/custom-react-scripts/customizers/webpack-plugins.js
react_pages/nodejs/config/custom-react-scripts/options/extract-text-plugin-options.js
react_pages/nodejs/config/custom-react-scripts/options/postcss-options.js
react_pages/nodejs/config/custom-react-scripts/utils/map-object.js
react_pages/nodejs/config/custom-react-scripts/webpack-config/style-loader.js
react_pages/nodejs/config/jest/cssTransform.js
react_pages/nodejs/config/jest/fileTransform.js
react_pages/nodejs/public/favicon.ico
react_pages/nodejs/public/index.html
react_pages/nodejs/public/manifest.json
react_pages/nodejs/scripts/build.js
react_pages/nodejs/scripts/getProcessForPort.js
react_pages/nodejs/scripts/modify-readmes.js
react_pages/nodejs/scripts/react_pages.js
react_pages/nodejs/scripts/start.js
react_pages/nodejs/scripts/test.js
react_pages/nodejs/src/App.css
react_pages/nodejs/src/App.js
react_pages/nodejs/src/App.test.js
react_pages/nodejs/src/index.css
react_pages-0.3.2.dist-info/METADATA
react_pages-0.3.2.dist-info/RECORD
react_pages-0.3.2.dist-info/WHEEL
react_pages-0.3.2.dist-info/entry_points.txt
react_pages-0.3.2.dist-info/top_level.txt
