Metadata-Version: 2.1
Name: react-pages
Version: 0.3.2
Summary: A zero-fuss way to create non single page apps with react.
Home-page: https://github.com/pycampers/react-pages
Author: devxpy
Author-email: devxpy@gmail.com
License: MIT
Platform: UNKNOWN
Classifier: License :: OSI Approved :: MIT License
Classifier: Programming Language :: Python
Classifier: Programming Language :: Python :: 3
Classifier: Programming Language :: Python :: 3.6
Classifier: Programming Language :: Python :: Implementation :: CPython
Classifier: Programming Language :: Python :: Implementation :: PyPy
Requires-Python: >=3.6.0
Provides-Extra: faster json
Provides-Extra: django integration
Requires-Dist: click
Requires-Dist: crayons
Requires-Dist: halo
Requires-Dist: python-dotenv
Provides-Extra: django integration
Requires-Dist: django; extra == 'django integration'
Provides-Extra: faster json
Requires-Dist: ujson; extra == 'faster json'
